idiota/__init__.py
idiota/base.py
idiota/cli.py
idiota/data.py
idiota/diff.py
idiota/remote.py
idiota-1.1.0.dist-info/LICENSE
idiota-1.1.0.dist-info/METADATA
idiota-1.1.0.dist-info/WHEEL
idiota-1.1.0.dist-info/entry_points.txt
idiota-1.1.0.dist-info/top_level.txt
idiota-1.1.0.dist-info/RECORD
