Metadata-Version: 2.1
Name: idiota
Version: 1.1.0
Summary: idiota is a minimal version control system built on python
Home-page: https://github.com/prakashsellathurai/idiota
Author: Prakash Sellathurai
Author-email: prakashsellathurai@gmail.com
License: UNKNOWN
Platform: UNKNOWN
License-File: LICENSE
